webuidriver/__about__.py
webuidriver/__init__.py
webuidriver/actions.py
webuidriver/cli.py
webuidriver/driver.py
webuidriver/chrome/__init__.py
webuidriver/chrome/options.py
webuidriver/chrome/webdriver.py
webuidriver/edge/__init__.py
webuidriver/edge/webdriver.py
webuidriver/firefox/__init__.py
webuidriver/firefox/firefox_profile.py
webuidriver/firefox/webdriver.py
webuidriver/ie/__init__.py
webuidriver/ie/webdriver.py
webuidriver/opera/__init__.py
webuidriver/opera/webdriver.py
webuidriver/remote/SeleniumHatch.py
webuidriver/remote/SeleniumJar.py
webuidriver/remote/__init__.py
webuidriver/remote/wait_until.py
webuidriver/remote/webdriver.py
webuidriver/safari/__init__.py
webuidriver/safari/webdriver.py
rtsf_web-1.4.1.dist-info/LICENSE
rtsf_web-1.4.1.dist-info/METADATA
rtsf_web-1.4.1.dist-info/WHEEL
rtsf_web-1.4.1.dist-info/entry_points.txt
rtsf_web-1.4.1.dist-info/top_level.txt
rtsf_web-1.4.1.dist-info/RECORD
