Metadata-Version: 2.1
Name: rtsf-web
Version: 1.4.1
Summary: only for web ui test, base on rtsf 
Home-page: https://github.com/RockFeng0/rtsf-web
Author: RockFeng0
Author-email: 281589463@qq.com
License: MIT
Keywords: test web ui
Platform: UNKNOWN
Requires-Python: >=2.7, !=3.0.*, !=3.1.*, !=3.2.*, !=3.3.*, <4
Requires-Dist: selenium !=4.17,>=3.141.0
Requires-Dist: requests
Requires-Dist: rtsf
